himport/__init__.py
himport/himport.py
himport/utils.py
himport-0.0.1.dist-info/LICENSE
himport-0.0.1.dist-info/METADATA
himport-0.0.1.dist-info/WHEEL
himport-0.0.1.dist-info/top_level.txt
himport-0.0.1.dist-info/RECORD
