Metadata-Version: 2.1
Name: himport
Version: 0.0.1
Summary: My package description
Author: Combo Gang
Author-email: contact@combogang.xom
License: MIT
Classifier: Programming Language :: Python :: 3
License-File: LICENSE
Requires-Dist: requests
